{
  "config": {
    "configFile": "/Users/pavel/WebstormProjects/TypeScriptPlaywrightAppTest/playwright.config.ts",
    "rootDir": "/Users/pavel/WebstormProjects/TypeScriptPlaywrightAppTest/tests",
    "forbidOnly": false,
    "fullyParallel": false,
    "globalSetup": null,
    "globalTeardown": null,
    "globalTimeout": 0,
    "grep": {},
    "grepInvert": null,
    "maxFailures": 0,
    "metadata": {
      "actualWorkers": 1
    },
    "preserveOutput": "always",
    "reporter": [
      [
        "list",
        null
      ],
      [
        "json",
        {
          "outputFile": "reports/json-report/report.json"
        }
      ],
      [
        "html",
        {
          "outputFolder": "reports/html-report/",
          "open": "never"
        }
      ],
      [
        "junit",
        {
          "outputFile": "reports/junit-report/report.xml"
        }
      ],
      [
        "/Users/pavel/WebstormProjects/TypeScriptPlaywrightAppTest/node_modules/@estruyf/github-actions-reporter/dist/index.js",
        null
      ],
      [
        "/Users/pavel/WebstormProjects/TypeScriptPlaywrightAppTest/node_modules/monocart-reporter/lib/index.js",
        {
          "name": "My Test Report",
          "outputFile": "reports/monocart-report/index.html"
        }
      ],
      [
        "/Users/pavel/WebstormProjects/TypeScriptPlaywrightAppTest/node_modules/allure-playwright/dist/cjs/index.js",
        {
          "resultsDir": "allure-results",
          "detail": true,
          "suiteTitle": true,
          "categories": [
            {
              "name": "Reports",
              "messageRegex": "bar",
              "traceRegex": "baz"
            }
          ],
          "environmentInfo": {
            "os_platform": "darwin",
            "os_release": "23.6.0",
            "os_version": "Darwin Kernel Version 23.6.0: Thu Dec 19 20:44:50 PST 2024; root:xnu-10063.141.1.703.2~1/RELEASE_X86_64",
            "node_version": "v20.17.0",
            "process_platform": "darwin"
          },
          "storeTrends": true
        }
      ]
    ],
    "reportSlowTests": {
      "max": 5,
      "threshold": 15000
    },
    "quiet": false,
    "projects": [
      {
        "outputDir": "/Users/pavel/WebstormProjects/TypeScriptPlaywrightAppTest/test-results",
        "repeatEach": 1,
        "retries": 0,
        "metadata": {},
        "id": "chromium",
        "name": "chromium",
        "testDir": "/Users/pavel/WebstormProjects/TypeScriptPlaywrightAppTest/tests",
        "testIgnore": [],
        "testMatch": [
          "**/*.@(spec|test).?(c|m)[jt]s?(x)"
        ],
        "timeout": 60000
      }
    ],
    "shard": null,
    "updateSnapshots": "missing",
    "updateSourceMethod": "patch",
    "version": "1.50.0",
    "workers": 2,
    "webServer": null
  },
  "suites": [
    {
      "title": "search.func.spec.ts",
      "file": "search.func.spec.ts",
      "column": 0,
      "line": 0,
      "specs": [],
      "suites": [
        {
          "title": "Should Search Users By Search Criteria",
          "file": "search.func.spec.ts",
          "line": 28,
          "column": 10,
          "specs": [
            {
              "title": "Search User With Unique First Name: Run_19",
              "ok": true,
              "tags": [],
              "tests": [
                {
                  "timeout": 60000,
                  "annotations": [],
                  "expectedStatus": "passed",
                  "projectId": "chromium",
                  "projectName": "chromium",
                  "results": [
                    {
                      "workerIndex": 0,
                      "status": "passed",
                      "duration": 1429,
                      "errors": [],
                      "stdout": [],
                      "stderr": [],
                      "retry": 0,
                      "startTime": "2025-02-09T17:16:14.365Z",
                      "attachments": []
                    }
                  ],
                  "status": "expected"
                }
              ],
              "id": "f0c549f384fac9c1ee05-68acbcba86a1fd2c1728",
              "file": "search.func.spec.ts",
              "line": 38,
              "column": 13
            }
          ]
        }
      ]
    }
  ],
  "errors": [],
  "stats": {
    "startTime": "2025-02-09T17:16:13.692Z",
    "duration": 2380.643,
    "expected": 1,
    "skipped": 0,
    "unexpected": 0,
    "flaky": 0
  }
}